infi.logs_collector-0.1.21-py2.7-nspkg.pth
infi/logs_collector/__init__.py
infi/logs_collector/__version__.py
infi/logs_collector/items.py
infi/logs_collector/util.py
infi/logs_collector/collectables/__init__.py
infi/logs_collector/collectables/windows/__init__.py
infi/logs_collector/scripts/__init__.py
infi.logs_collector-0.1.21.dist-info/LICENSE
infi.logs_collector-0.1.21.dist-info/METADATA
infi.logs_collector-0.1.21.dist-info/WHEEL
infi.logs_collector-0.1.21.dist-info/entry_points.txt
infi.logs_collector-0.1.21.dist-info/namespace_packages.txt
infi.logs_collector-0.1.21.dist-info/top_level.txt
infi.logs_collector-0.1.21.dist-info/RECORD
