Metadata-Version: 2.1
Name: infi.logs-collector
Version: 0.1.21
Summary: helper for logs collection
Home-page: https://github.com/Infinidat/infi.logs_collector
Author: Arnon Yaari
Author-email: arnony@infinidat.com
License: BSD
Platform: UNKNOWN
Classifier: Intended Audience :: Developers
Classifier: Intended Audience :: System Administrators
Classifier: License :: OSI Approved :: BSD License
Classifier: Operating System :: OS Independent
Classifier: Programming Language :: Python
Classifier: Programming Language :: Python :: 2
Classifier: Programming Language :: Python :: 3
Classifier: Topic :: Software Development :: Libraries :: Python Modules
Requires-Dist: colorama
Requires-Dist: infi.blocking
Requires-Dist: infi.eventlog
Requires-Dist: infi.execute
Requires-Dist: infi.pyutils
Requires-Dist: infi.traceback
Requires-Dist: setuptools
Requires-Dist: six
